elsa/__init__.py
elsa/_cli.py
elsa/_deployment.py
elsa/_shutdown.py
elsa-0.1.6.dist-info/LICENSE
elsa-0.1.6.dist-info/METADATA
elsa-0.1.6.dist-info/WHEEL
elsa-0.1.6.dist-info/top_level.txt
elsa-0.1.6.dist-info/RECORD
