Metadata-Version: 2.1
Name: elsa
Version: 0.1.6
Summary: Helper module for Frozen-Flask based websites
Home-page: https://github.com/pyvec/elsa
Author: Miro Hrončok
Author-email: miro@hroncok.cz
License: MIT
Keywords: flask web github
Platform: UNKNOWN
Classifier: Development Status :: 3 - Alpha
Classifier: Intended Audience :: Developers
Classifier: License :: OSI Approved :: MIT License
Classifier: Operating System :: MacOS :: MacOS X
Classifier: Operating System :: Microsoft :: Windows
Classifier: Operating System :: POSIX :: Linux
Classifier: Programming Language :: Python
Classifier: Programming Language :: Python :: Implementation :: CPython
Classifier: Programming Language :: Python :: Implementation :: PyPy
Classifier: Programming Language :: Python :: 3
Classifier: Programming Language :: Python :: 3 :: Only
Classifier: Programming Language :: Python :: 3.5
Classifier: Programming Language :: Python :: 3.6
Classifier: Programming Language :: Python :: 3.7
Classifier: Programming Language :: Python :: 3.8
Classifier: Programming Language :: Python :: 3.9
Classifier: Topic :: Internet :: WWW/HTTP
Requires-Dist: click
Requires-Dist: Flask
Requires-Dist: Frozen-Flask (>=0.15)
Requires-Dist: ghp-import
